aboutcode/pipeline/CHANGELOG.md
aboutcode/pipeline/README.md
aboutcode/pipeline/RELEASE.md
aboutcode/pipeline/__init__.py
aboutcode_pipeline-0.2.1.dist-info/WHEEL
aboutcode_pipeline-0.2.1.dist-info/METADATA
aboutcode_pipeline-0.2.1.dist-info/LICENSE
aboutcode_pipeline-0.2.1.dist-info/NOTICE
aboutcode_pipeline-0.2.1.dist-info/RECORD
