Metadata-Version: 2.1
Name: aboutcode.pipeline
Version: 0.2.1
Summary: AboutCode Pipeline library. Execute code in steps.
Keywords: open source,pipeline,scancode
Author-email: "nexB. Inc. and others" <info@aboutcode.org>
Requires-Python: >=3.9
Classifier: Development Status :: 4 - Beta
Classifier: Intended Audience :: Developers
Classifier: Programming Language :: Python :: 3
Classifier: Programming Language :: Python :: 3 :: Only
Classifier: Programming Language :: Python :: 3.9
Classifier: Programming Language :: Python :: 3.10
Classifier: Programming Language :: Python :: 3.11
Classifier: Programming Language :: Python :: 3.12
Classifier: Topic :: Software Development
Classifier: Topic :: Utilities
Project-URL: Changelog, https://github.com/aboutcode-org/scancode.io/tree/main/aboutcode/pipeline/CHANGELOG.md
Project-URL: Documentation, https://scancodeio.readthedocs.io/
Project-URL: Homepage, https://github.com/aboutcode-org/scancode.io
Project-URL: Issues, https://github.com/aboutcode-org/scancode.io/issues
Project-URL: Repository, https://github.com/aboutcode-org/scancode.io/tree/main/aboutcode/pipeline
